LICENSE
MANIFEST.in
README.md
pyproject.toml
requirements.txt
src/andorcal/__init__.py
src/andorcal/calendar_util.py
src/andorcal/const.py
src/andorcal/dst.py
src/andorcal/time_dict.py
src/andorcal.egg-info/PKG-INFO
src/andorcal.egg-info/SOURCES.txt
src/andorcal.egg-info/dependency_links.txt
src/andorcal.egg-info/requires.txt
src/andorcal.egg-info/top_level.txt
src/tests/difference.py
src/tests/test_create_calendar.py
src/tests/test_dst.py
src/tests/test_time_dict.py