Metadata-Version: 2.1
Name: andorcal
Version: 0.0.7
Summary: Calendar utility for Andor. Package to generate calendar data based on input dates
Author-email: Noah Hatakeyama <noah@kikker.nl>
Project-URL: Homepage, https://github.com/Kikker-Energie/ka-calendar-utils
Classifier: Programming Language :: Python :: 3
Classifier: Operating System :: OS Independent
Requires-Python: >=3.9
License-File: LICENSE
Requires-Dist: keyring>=25.0.1
Requires-Dist: keyrings.google-artifactregistry-auth>=1.1.2
Requires-Dist: pylint>=3.2.3
Requires-Dist: pytest>=8.2.2
Requires-Dist: setuptools>=70.0.0
Requires-Dist: tox>=4.15.1
Requires-Dist: twine>=5.1.0
Requires-Dist: wheel>=0.42.0
Requires-Dist: pandas>=2.2.2
